rl_rock-1.1.0.dist-info/licenses/LICENSE
rock/__init__.py
rock/_codes.py
rock/config.py
rock/env_vars.py
rock/logger.py
rock/actions/__init__.py
rock/actions/response.py
rock/actions/envs/base.py
rock/actions/envs/request.py
rock/actions/envs/response.py
rock/actions/sandbox/base.py
rock/actions/sandbox/config.py
rock/actions/sandbox/request.py
rock/actions/sandbox/response.py
rock/actions/sandbox/sandbox_info.py
rock/admin/main.py
rock/admin/core/db_provider.py
rock/admin/core/ray_service.py
rock/admin/core/redis_key.py
rock/admin/core/sandbox_table.py
rock/admin/core/schema.py
rock/admin/entrypoints/sandbox_api.py
rock/admin/entrypoints/sandbox_proxy_api.py
rock/admin/entrypoints/warmup_api.py
rock/admin/gem/api.py
rock/admin/metrics/constants.py
rock/admin/metrics/decorator.py
rock/admin/metrics/gc_view_instrument_match.py
rock/admin/metrics/monitor.py
rock/admin/proto/request.py
rock/admin/proto/response.py
rock/admin/proto/task.py
rock/cli/config.py
rock/cli/loader.py
rock/cli/main.py
rock/cli/command/admin.py
rock/cli/command/command.py
rock/cli/command/crypto.py
rock/cli/command/image.py
rock/cli/command/model_service.py
rock/common/constants.py
rock/deployments/__init__.py
rock/deployments/abstract.py
rock/deployments/config.py
rock/deployments/constants.py
rock/deployments/docker.py
rock/deployments/local.py
rock/deployments/manager.py
rock/deployments/ray.py
rock/deployments/remote.py
rock/deployments/runtime_env.py
rock/deployments/sandbox_validator.py
rock/deployments/status.py
rock/deployments/hooks/__init__.py
rock/deployments/hooks/abstract.py
rock/envhub/__init__.py
rock/envhub/server.py
rock/envhub/api/__init__.py
rock/envhub/api/schemas.py
rock/envhub/core/__init__.py
rock/envhub/core/envhub.py
rock/envhub/database/__init__.py
rock/envhub/database/base.py
rock/envhub/database/docker_env.py
rock/rocklet/__init__.py
rock/rocklet/__main__.py
rock/rocklet/exceptions.py
rock/rocklet/local_api.py
rock/rocklet/local_sandbox.py
rock/rocklet/server.py
rock/rocklet/local_files/docker_run.sh
rl_rock-1.1.0.dist-info/METADATA
rl_rock-1.1.0.dist-info/WHEEL
rl_rock-1.1.0.dist-info/entry_points.txt
rl_rock-1.1.0.dist-info/top_level.txt
rl_rock-1.1.0.dist-info/RECORD
