Metadata-Version: 2.4
Name: rl-rock
Version: 1.1.0
Summary: ROCK-Reinforcement Open Construction Kit
Author: chatos@alibaba
Requires-Python: <4.0,>=3.10
License-File: LICENSE
Requires-Dist: httpx
Requires-Dist: uuid
Requires-Dist: anyio
Requires-Dist: build
Requires-Dist: opentelemetry-api
Requires-Dist: opentelemetry-sdk
Requires-Dist: opentelemetry-exporter-otlp
Requires-Dist: opentelemetry-exporter-prometheus
Requires-Dist: requests
Requires-Dist: pydantic
Requires-Dist: python-multipart
Requires-Dist: rich
Requires-Dist: oss2
Requires-Dist: pyyaml
Requires-Dist: tzdata
Provides-Extra: admin
Requires-Dist: rl-rock[rocklet]; extra == "admin"
Requires-Dist: ray[default]==2.43.0; extra == "admin"
Requires-Dist: nacos-sdk-python>=0.1.14; extra == "admin"
Requires-Dist: redis; extra == "admin"
Requires-Dist: apscheduler; extra == "admin"
Requires-Dist: websockets>=15.0.1; extra == "admin"
Requires-Dist: aiohttp>=3.12.15; extra == "admin"
Requires-Dist: alibabacloud_cr20181201==2.0.5; extra == "admin"
Requires-Dist: sqlmodel; extra == "admin"
Requires-Dist: aiosqlite; extra == "admin"
Requires-Dist: boto3; extra == "admin"
Requires-Dist: ray[default]==2.43.0; extra == "admin"
Requires-Dist: pip; extra == "admin"
Requires-Dist: cryptography==39.0.1; extra == "admin"
Provides-Extra: rocklet
Requires-Dist: fastapi; extra == "rocklet"
Requires-Dist: uvicorn; extra == "rocklet"
Requires-Dist: pexpect; extra == "rocklet"
Requires-Dist: bashlex; extra == "rocklet"
Requires-Dist: psutil; extra == "rocklet"
Requires-Dist: twisted; extra == "rocklet"
Requires-Dist: gem-llm>=0.1.0; extra == "rocklet"
Provides-Extra: sandbox-actor
Requires-Dist: apscheduler>=3.11.0; extra == "sandbox-actor"
Requires-Dist: gem-llm>=0.1.0; extra == "sandbox-actor"
Requires-Dist: sqlmodel; extra == "sandbox-actor"
Requires-Dist: nacos-sdk-python>=0.1.14; extra == "sandbox-actor"
Requires-Dist: redis; extra == "sandbox-actor"
Provides-Extra: builder
Requires-Dist: swebench; extra == "builder"
Requires-Dist: gem-llm>=0.1.0; extra == "builder"
Requires-Dist: docker; extra == "builder"
Provides-Extra: model-service
Requires-Dist: fastapi; extra == "model-service"
Requires-Dist: uvicorn; extra == "model-service"
Requires-Dist: psutil; extra == "model-service"
Requires-Dist: swebench; extra == "model-service"
Requires-Dist: alibabacloud_cr20181201==2.0.5; extra == "model-service"
Provides-Extra: all
Requires-Dist: rl-rock[admin]; extra == "all"
Requires-Dist: rl-rock[rocklet]; extra == "all"
Requires-Dist: rl-rock[builder]; extra == "all"
Dynamic: license-file
